LICENSE
README.md
setup.py
CVE_2024_4956.egg-info/PKG-INFO
CVE_2024_4956.egg-info/SOURCES.txt
CVE_2024_4956.egg-info/dependency_links.txt
CVE_2024_4956.egg-info/entry_points.txt
CVE_2024_4956.egg-info/requires.txt
CVE_2024_4956.egg-info/top_level.txt
cve20244956/__init__.py
cve20244956/main.py
cve20244956/includes/__init__.py
cve20244956/includes/bot.py
cve20244956/includes/filereader.py
cve20244956/includes/scan.py
cve20244956/includes/writefile.py
cve20244956/utils/__init__.py
cve20244956/utils/configure.py
cve20244956/utils/const.py
cve20244956/utils/helpers.py
cve20244956/utils/status.py